{"adult":false,"backdrop_path":"\/q05WV8DwEiyLbCgSVtg55RbUzou.jpg","belongs_to_collection":null,"budget":20000000,"genres":[{"id":28,"name":"Ação"},{"id":35,"name":"Comédia"},{"id":27,"name":"Terror"}],"homepage":"","id":1292695,"imdb_id":"tt31728330","origin_country":["US"],"original_language":"en","original_title":"They Will Kill You","overview":"Determinada a mudar de vida, uma mulher aceita um emprego como empregada doméstica no Virgil, um enorme prédio construído em Manhattan no princípio do século passado. O que ela não sabe é que, para além do luxo desmedido do edifício, existe ali uma comunidade secreta que celebra Satanás com rituais onde são feitos sacrifícios humanos. E isso talvez explique os boatos sobre várias pessoas que ali entraram e que foram dadas como desaparecidas. Mas há algo para o qual ninguém que ali vive está preparado: depois de vários anos na prisão, ela perdeu o medo e transformou-se numa lutadora prodigiosa.","popularity":131.6238,"poster_path":"\/z06uGrmybEx9AFTXZ8cVzOdcEqM.jpg","production_companies":[{"id":229398,"logo_path":null,"name":"Nocturna","origin_country":"US"},{"id":12,"logo_path":"\/2ycs64eqV5rqKYHyQK0GVoKGvfX.png","name":"New Line Cinema","origin_country":"US"},{"id":216687,"logo_path":"\/kKVYqekveOvLK1IgqdJojLjQvtu.png","name":"Domain Entertainment","origin_country":"US"},{"id":773,"logo_path":"\/qkcN6yZEyBw3cgO5DJu55LGEsf7.png","name":"Film Afrika","origin_country":"ZA"}],"production_countries":[{"iso_3166_1":"US","name":"United States of America"},{"iso_3166_1":"ZA","name":"South Africa"}],"release_date":"2026-03-25","revenue":18982152,"runtime":94,"softcore":false,"spoken_languages":[{"english_name":"English","iso_639_1":"en","name":"English"}],"status":"Released","tagline":"","title":"Eles Matam-te","video":false,"vote_average":6.717,"vote_count":406}